quart_libretranslate/__init__.py
quart_libretranslate/core.py
quart_libretranslate/error.py
quart_libretranslate/py.typed
quart_libretranslate/wrappers.py
quart_libretranslate-0.0.2.dist-info/LICENSE
quart_libretranslate-0.0.2.dist-info/METADATA
quart_libretranslate-0.0.2.dist-info/WHEEL
quart_libretranslate-0.0.2.dist-info/RECORD
