Metadata-Version: 2.1
Name: quart_libretranslate
Version: 0.0.2
Summary: LibreTranslate for Quart
Home-page: https://github.com/Quart-Addons/quart-libretranslate
License: MIT
Author: Chris Rood
Author-email: quart.addons@gmail.com
Requires-Python: >=3.8
Classifier: License :: OSI Approved :: MIT License
Classifier: Programming Language :: Python :: 3
Classifier: Programming Language :: Python :: 3.8
Classifier: Programming Language :: Python :: 3.9
Classifier: Programming Language :: Python :: 3.10
Classifier: Programming Language :: Python :: 3.11
Classifier: Programming Language :: Python :: 3.12
Requires-Dist: aiohttp (>=3.10.5)
Requires-Dist: quart (>=0.19.0)
Project-URL: Documentation, https://quart-libretranslate.readthedocs.io/en/latest/
Project-URL: Repository, https://github.com/Quart-Addons/quart-libretranslate
